sphinx_llms_txt_rw/__init__.py
sphinx_llms_txt_rw/collector.py
sphinx_llms_txt_rw/manager.py
sphinx_llms_txt_rw/processor.py
sphinx_llms_txt_rw/writer.py
sphinx_llms_txt_rw-0.5.4.dist-info/licenses/LICENSE
sphinx_llms_txt_rw-0.5.4.dist-info/METADATA
sphinx_llms_txt_rw-0.5.4.dist-info/WHEEL
sphinx_llms_txt_rw-0.5.4.dist-info/top_level.txt
sphinx_llms_txt_rw-0.5.4.dist-info/RECORD
