Metadata-Version: 2.4
Name: sphinx-llms-txt-rw
Version: 0.5.4
Summary: llms-full.txt generator for Sphinx
Author: Mladen Zagorac
Maintainer: Mladen Zagorac
License: MIT
Project-URL: download, https://pypi.org/project/sphinx-llms-txt-rw/
Project-URL: source, https://github.com/jdillard/sphinx-llms-txt-rw
Project-URL: changelog, https://github.com/jdillard/sphinx-llms-txt-rw/blob/master/CHANGELOG.rst
Classifier: Framework :: Sphinx :: Extension
Classifier: License :: OSI Approved :: MIT License
Classifier: Programming Language :: Python :: 3.9
Classifier: Programming Language :: Python :: 3.10
Classifier: Programming Language :: Python :: 3.11
Classifier: Programming Language :: Python :: 3.12
Classifier: Topic :: Documentation :: Sphinx
Requires-Python: >=3.9
License-File: LICENSE
Requires-Dist: sphinx
Dynamic: license-file
